encore_python/__init__.py
encore_python/client/__init__.py
encore_python/client/encore.py
encore_python/client/parsing.py
encore_python/types/__init__.py
encore_python/types/request.py
encore_python/types/response.py
encore_python/types/shared.py
encore_python-1.1.0.dist-info/LICENSE
encore_python-1.1.0.dist-info/METADATA
encore_python-1.1.0.dist-info/WHEEL
encore_python-1.1.0.dist-info/top_level.txt
encore_python-1.1.0.dist-info/RECORD
