Metadata-Version: 2.1
Name: encore_python
Version: 1.1.0
Summary: Python API wrapper for encore.us
Author-email: Josh Mcdaniel <80354972+joshrmcdaniel@users.noreply.github.com>
License: MIT License
Project-URL: homepage, https://github.com/joshrmcdaniel/encore-python
Keywords: sng,.sng,clone hero,ch,file,sng-format,sng-parse
Classifier: Intended Audience :: Developers
Classifier: License :: OSI Approved :: MIT License
Classifier: Development Status :: 5 - Production/Stable
Classifier: Programming Language :: Python :: 3
Classifier: Programming Language :: Python :: 3.10
Classifier: Programming Language :: Python :: 3.11
Classifier: Programming Language :: Python :: 3.12
Requires-Python: >=3.10
License-File: LICENSE
Requires-Dist: requests
Requires-Dist: jsonobject
Requires-Dist: sng-parser ==1.1.0
